streamlit_location/__init__.py
streamlit_location/frontend/build/asset-manifest.json
streamlit_location/frontend/build/bootstrap.min.css
streamlit_location/frontend/build/index.html
streamlit_location/frontend/build/precache-manifest.a11dc30c29defd85fe44e0a6cfa7c651.js
streamlit_location/frontend/build/service-worker.js
streamlit_location/frontend/build/static/js/2.330a583f.chunk.js
streamlit_location/frontend/build/static/js/2.330a583f.chunk.js.LICENSE.txt
streamlit_location/frontend/build/static/js/2.330a583f.chunk.js.map
streamlit_location/frontend/build/static/js/main.44a07802.chunk.js
streamlit_location/frontend/build/static/js/main.44a07802.chunk.js.LICENSE.txt
streamlit_location/frontend/build/static/js/main.44a07802.chunk.js.map
streamlit_location/frontend/build/static/js/runtime-main.085ce4f3.js
streamlit_location/frontend/build/static/js/runtime-main.085ce4f3.js.map
streamlit_location-0.0.2.dist-info/LICENSE
streamlit_location-0.0.2.dist-info/METADATA
streamlit_location-0.0.2.dist-info/WHEEL
streamlit_location-0.0.2.dist-info/top_level.txt
streamlit_location-0.0.2.dist-info/RECORD
